Test/__init__.py
panmetrics/__init__.py
panmetrics/classification.py
panmetrics/clustering.py
panmetrics/imagetoimage.py
panmetrics/regression.py
panmetrics/segmentation.py
panmetrics/utils.py
panmetrics-0.1.1.dist-info/licenses/LICENSE
panmetrics-0.1.1.dist-info/METADATA
panmetrics-0.1.1.dist-info/WHEEL
panmetrics-0.1.1.dist-info/top_level.txt
panmetrics-0.1.1.dist-info/RECORD
